keystone_message_broker/__about__.py
keystone_message_broker/__init__.py
keystone_message_broker/models.py
keystone_message_broker/nats_service.py
keystone_message_broker-3.8.2a1.dist-info/METADATA
keystone_message_broker-3.8.2a1.dist-info/WHEEL
keystone_message_broker-3.8.2a1.dist-info/licenses/LICENSE.txt
keystone_message_broker-3.8.2a1.dist-info/RECORD
