Metadata-Version: 2.3
Name: keystone-message-broker
Version: 3.8.2a1
Author-email: Purple Jay LLC <developers@purplejay.io>
License: MIT
Classifier: Development Status :: 4 - Beta
Classifier: Programming Language :: Python
Classifier: Programming Language :: Python :: 3.12
Classifier: Programming Language :: Python :: Implementation :: CPython
Classifier: Programming Language :: Python :: Implementation :: PyPy
Requires-Python: >=3.12
Requires-Dist: fastapi
Requires-Dist: loguru
Requires-Dist: nats-py
